odoo/addons/sale_auto_remove_zero_quantity_lines/README.rst
odoo/addons/sale_auto_remove_zero_quantity_lines/__init__.py
odoo/addons/sale_auto_remove_zero_quantity_lines/__manifest__.py
odoo/addons/sale_auto_remove_zero_quantity_lines/i18n/de.po
odoo/addons/sale_auto_remove_zero_quantity_lines/i18n/fr.po
odoo/addons/sale_auto_remove_zero_quantity_lines/i18n/hr.po
odoo/addons/sale_auto_remove_zero_quantity_lines/i18n/it.po
odoo/addons/sale_auto_remove_zero_quantity_lines/i18n/sale_auto_remove_zero_quantity_lines.pot
odoo/addons/sale_auto_remove_zero_quantity_lines/models/__init__.py
odoo/addons/sale_auto_remove_zero_quantity_lines/models/res_company.py
odoo/addons/sale_auto_remove_zero_quantity_lines/models/res_config_settings.py
odoo/addons/sale_auto_remove_zero_quantity_lines/models/sale_order.py
odoo/addons/sale_auto_remove_zero_quantity_lines/readme/CONFIGURE.rst
odoo/addons/sale_auto_remove_zero_quantity_lines/readme/CONTRIBUTORS.rst
odoo/addons/sale_auto_remove_zero_quantity_lines/readme/DESCRIPTION.rst
odoo/addons/sale_auto_remove_zero_quantity_lines/static/description/icon.png
odoo/addons/sale_auto_remove_zero_quantity_lines/static/description/index.html
odoo/addons/sale_auto_remove_zero_quantity_lines/tests/__init__.py
odoo/addons/sale_auto_remove_zero_quantity_lines/tests/test_sale_auto_remove_zero_quantity_lines.py
odoo/addons/sale_auto_remove_zero_quantity_lines/views/res_config_settings_views.xml
odoo_addon_sale_auto_remove_zero_quantity_lines-16.0.1.1.0.4.dist-info/METADATA
odoo_addon_sale_auto_remove_zero_quantity_lines-16.0.1.1.0.4.dist-info/WHEEL
odoo_addon_sale_auto_remove_zero_quantity_lines-16.0.1.1.0.4.dist-info/top_level.txt
odoo_addon_sale_auto_remove_zero_quantity_lines-16.0.1.1.0.4.dist-info/RECORD
